TorchVersionist/__init__.py
TorchVersionist/main.py
TorchVersionist/model_analyzer.py
TorchVersionist/model_loader.py
TorchVersionist/model_manager.py
TorchVersionist/training_metric.py
TorchVersionist/training_metric_tracker.py
torchversionist-0.0.1.dist-info/LICENSE
torchversionist-0.0.1.dist-info/METADATA
torchversionist-0.0.1.dist-info/WHEEL
torchversionist-0.0.1.dist-info/top_level.txt
torchversionist-0.0.1.dist-info/RECORD
