Metadata-Version: 2.1
Name: torchversionist
Version: 0.0.1
Summary: A package for managing PyTorch model versions, metadata, and metrics.
Home-page: https://github.com/jaxels20/ModelKeeper
Author: Jeppe Berg Axelsen
Author-email: xfm82gtn@gmail.com
Classifier: Programming Language :: Python :: 3
Classifier: License :: OSI Approved :: MIT License
Classifier: Operating System :: OS Independent
Requires-Python: >=3.10
License-File: LICENSE
